{"38": {"user": "GinLee", "task": "A", "time": 1732704968}, "39": {"user": "GinLee", "task": "A", "time": 1732705067}, "40": {"user": "GinLee", "task": "A", "time": 1732705246}, "41": {"user": "GinLee", "task": "A", "time": 1732705354}, "42": {"user": "GinLee", "task": "A", "time": 1732705924}, "43": {"user": "GinLee", "task": "C", "time": 1732709129}, "44": {"user": "GinLee", "task": "C", "time": 1732709203}, "45": {"user": "GinLee", "task": "C", "time": 1732709324}, "46": {"user": "GinLee", "task": "D", "time": 1732709899}, "47": {"user": "GinLee", "task": "D", "time": 1732709961}, "48": {"user": "GinLee", "task": "A", "time": 1732710533}, "49": {"user": "GinLee", "task": "A", "time": 1732710648}, "50": {"user": "GinLee", "task": "E", "time": 1732711745}, "51": {"user": "GinLee", "task": "E", "time": 1732711807}, "52": {"user": "GinLee", "task": "E", "time": 1732711923}, "53": {"user": "GinLee", "task": "E", "time": 1732712485}, "54": {"user": "GinLee", "task": "E", "time": 1732712715}, "55": {"user": "GinLee", "task": "E", "time": 1732712842}, "56": {"user": "GinLee", "task": "E", "time": 1732713009}, "57": {"user": "GinLee", "task": "A", "time": 1732713601}, "58": {"user": "GinLee", "task": "A", "time": 1732713665}, "59": {"user": "GinLee", "task": "C", "time": 1732713814}, "60": {"user": "brown_5ftoad", "task": "D", "time": 1732716193}, "61": {"user": "tingpeng1055", "task": "A", "time": 1732716392}, "62": {"user": "brown_5ftoad", "task": "C", "time": 1732718025}, "63": {"user": "brown_5ftoad", "task": "C", "time": 1732718089}, "64": {"user": "mochaowo", "task": "E", "time": 1732948926}, "65": {"user": "mochaowo", "task": "E", "time": 1732949130}, "66": {"user": "mochaowo", "task": "E", "time": 1732949429}, "67": {"user": "huangallen", "task": "C", "time": 1732950205}, "68": {"user": "huangallen", "task": "C", "time": 1732950398}, "69": {"user": "JC0713", "task": "B", "time": 1732951883}, "70": {"user": "huangallen", "task": "B", "time": 1732952724}, "71": {"user": "t6stks", "task": "E", "time": 1732953070}, "72": {"user": "huangallen", "task": "B", "time": 1732953151}, "73": {"user": "huangallen", "task": "B", "time": 1732953252}, "74": {"user": "huangallen", "task": "B", "time": 1732953609}, "75": {"user": "t6stks", "task": "C", "time": 1732954118}, "76": {"user": "huangallen", "task": "B", "time": 1732954315}, "77": {"user": "huangallen", "task": "B", "time": 1732954455}, "78": {"user": "huangallen", "task": "D", "time": 1732954951}, "79": {"user": "huangallen", "task": "B", "time": 1732955045}, "80": {"user": "huangallen", "task": "B", "time": 1732955314}, "81": {"user": "huangallen", "task": "B", "time": 1732955529}, "82": {"user": "t6stks", "task": "D", "time": 1732955731}, "83": {"user": "huangallen", "task": "B", "time": 1732955754}, "84": {"user": "huangallen", "task": "B", "time": 1732955822}, "85": {"user": "huangallen", "task": "B", "time": 1732955891}, "86": {"user": "huangallen", "task": "B", "time": 1732955953}, "87": {"user": "t6stks", "task": "D", "time": 1732956287}, "88": {"user": "JC0713", "task": "A", "time": 1732956349}, "89": {"user": "JC0713", "task": "C", "time": 1732956411}, "90": {"user": "JC0713", "task": "C", "time": 1732956549}, "91": {"user": "t6stks", "task": "D", "time": 1732956589}, "92": {"user": "t6stks", "task": "D", "time": 1732956663}, "93": {"user": "t6stks", "task": "D", "time": 1732957091}, "94": {"user": "t6stks", "task": "D", "time": 1732957155}, "95": {"user": "t6stks", "task": "D", "time": 1732957221}, "96": {"user": "t6stks", "task": "D", "time": 1732957404}, "97": {"user": "t6stks", "task": "D", "time": 1732957467}, "98": {"user": "t6stks", "task": "D", "time": 1732957533}, "99": {"user": "t6stks", "task": "A", "time": 1732957969}, "100": {"user": "t6stks", "task": "A", "time": 1732958730}, "101": {"user": "t6stks", "task": "A", "time": 1732958830}, "102": {"user": "t6stks", "task": "A", "time": 1732958977}}